comfyui_workflow_templates_core/__init__.py
comfyui_workflow_templates_core/loader.py
comfyui_workflow_templates_core/manifest.json
comfyui_workflow_templates_core-0.3.88.dist-info/METADATA
comfyui_workflow_templates_core-0.3.88.dist-info/WHEEL
comfyui_workflow_templates_core-0.3.88.dist-info/top_level.txt
comfyui_workflow_templates_core-0.3.88.dist-info/RECORD
