Metadata-Version: 2.4
Name: comfyui-workflow-templates-core
Version: 0.3.88
Summary: Core helpers for ComfyUI workflow templates
License-Expression: MIT
Requires-Python: >=3.9
